my_own_package/__init__.py
maria_proiect_hello-0.2.0.dist-info/METADATA
maria_proiect_hello-0.2.0.dist-info/WHEEL
maria_proiect_hello-0.2.0.dist-info/top_level.txt
maria_proiect_hello-0.2.0.dist-info/RECORD
