Metadata-Version: 2.1
Name: maria-proiect-hello
Version: 0.2.0
Summary: says hello to user
Author: Maria V.
Author-email: v.mariavalentina92@gmail.com
License: UNKNOWN
Platform: UNKNOWN
